topis_aDRIJA/__init__.py
topis_aDRIJA/topis1.py
TOPSIS_Adrija_101803023-0.0.1.dist-info/METADATA
TOPSIS_Adrija_101803023-0.0.1.dist-info/WHEEL
TOPSIS_Adrija_101803023-0.0.1.dist-info/top_level.txt
TOPSIS_Adrija_101803023-0.0.1.dist-info/RECORD
