Metadata-Version: 2.1
Name: TOPSIS-Adrija-101803023
Version: 0.0.1
Summary: package that helps to calculate the topsis score
Home-page: UNKNOWN
Author: Adrija Akriti
Author-email: adrija.akriti@gmail.com
License: UNKNOWN
Platform: UNKNOWN
Classifier: Programming Language :: Python :: 3
Classifier: License :: OSI Approved :: MIT License
Classifier: Operating System :: OS Independent
Requires-Python: >=3.6
